table_update_create_scenario/__init__.py
table_update_create_scenario/frontend/build/asset-manifest.json
table_update_create_scenario/frontend/build/favicon.ico
table_update_create_scenario/frontend/build/index.html
table_update_create_scenario/frontend/build/logo192.png
table_update_create_scenario/frontend/build/logo512.png
table_update_create_scenario/frontend/build/manifest.json
table_update_create_scenario/frontend/build/robots.txt
table_update_create_scenario/frontend/build/static/css/main.b8d39620.css
table_update_create_scenario/frontend/build/static/css/main.b8d39620.css.map
table_update_create_scenario/frontend/build/static/js/main.aa608f8a.js
table_update_create_scenario/frontend/build/static/js/main.aa608f8a.js.LICENSE.txt
table_update_create_scenario/frontend/build/static/js/main.aa608f8a.js.map
table_update_create_scenario-5.2.0.dist-info/METADATA
table_update_create_scenario-5.2.0.dist-info/WHEEL
table_update_create_scenario-5.2.0.dist-info/top_level.txt
table_update_create_scenario-5.2.0.dist-info/RECORD
