Metadata-Version: 2.1
Name: table-update-create-scenario
Version: 5.2.0
Home-page: 
Author: 
Author-email: 
Requires-Python: >=3.6
Requires-Dist: streamlit >=0.66
